<?xml version="1.0" encoding="UTF-8" standalone="yes"?>
<configures>
	<configure id="[F1E1BC]石油每小时产量增加:[-][00FF00]+500[-]" value="[F1E1BC]石油每小时产量增加:[-][00FF00]+500[-]" />
	<configure id="[F1E1BC]金币每小时产量增加:[-][00FF00]+500[-]" value="[F1E1BC]金币每小时产量增加:[-][00FF00]+500[-]" />
	<configure id="[F1E1BC]钢铁每小时产量增加:[-][00FF00]+500[-]" value="[F1E1BC]钢铁每小时产量增加:[-][00FF00]+500[-]" />
	<configure id="[F1E1BC]稀矿每小时产量增加:[-][00FF00]+500[-]" value="[F1E1BC]稀矿每小时产量增加:[-][00FF00]+500[-]" />
	<configure id="[F1E1BC]石油每小时产量增加:[-][00FF00]+1000[-]" value="[F1E1BC]石油每小时产量增加:[-][00FF00]+1000[-]" />
	<configure id="[F1E1BC]金币每小时产量增加:[-][00FF00]+1000[-]" value="[F1E1BC]金币每小时产量增加:[-][00FF00]+1000[-]" />
	<configure id="[F1E1BC]钢铁每小时产量增加:[-][00FF00]+1000[-]" value="[F1E1BC]钢铁每小时产量增加:[-][00FF00]+1000[-]" />
	<configure id="[F1E1BC]稀矿每小时产量增加:[-][00FF00]+1000[-]" value="[F1E1BC]稀矿每小时产量增加:[-][00FF00]+1000[-]" />
	<configure id="[F1E1BC]石油每小时产量增加:[-][00FF00]+1%[-]" value="[F1E1BC]石油每小时产量增加:[-][00FF00]+1%[-]" />
	<configure id="[F1E1BC]金币每小时产量增加:[-][00FF00]+1%[-]" value="[F1E1BC]金币每小时产量增加:[-][00FF00]+1%[-]" />
	<configure id="[F1E1BC]钢铁每小时产量增加:[-][00FF00]+1%[-]" value="[F1E1BC]钢铁每小时产量增加:[-][00FF00]+1%[-]" />
	<configure id="[F1E1BC]稀矿每小时产量增加[-][00FF00]+1%[-]" value="[F1E1BC]稀矿每小时产量增加[-][00FF00]+1%[-]" />
	<configure id="[F1E1BC]石油每小时产量增加:[-][00FF00]+2%[-]" value="[F1E1BC]石油每小时产量增加:[-][00FF00]+2%[-]" />
	<configure id="[F1E1BC]金币每小时产量增加:[-][00FF00]+2%[-]" value="[F1E1BC]金币每小时产量增加:[-][00FF00]+2%[-]" />
	<configure id="[F1E1BC]钢铁每小时产量增加:[-][00FF00]+2%[-]" value="[F1E1BC]钢铁每小时产量增加:[-][00FF00]+2%[-]" />
	<configure id="[F1E1BC]稀矿每小时产量增加[-][00FF00]+2%[-]" value="[F1E1BC]稀矿每小时产量增加[-][00FF00]+2%[-]" />
	<configure id="[F1E1BC]石油每小时产量增加:[-][00FF00]+3%[-]" value="[F1E1BC]石油每小时产量增加:[-][00FF00]+3%[-]" />
	<configure id="[F1E1BC]金币每小时产量增加:[-][00FF00]+3%[-]" value="[F1E1BC]金币每小时产量增加:[-][00FF00]+3%[-]" />
	<configure id="[F1E1BC]钢铁每小时产量增加:[-][00FF00]+3%[-]" value="[F1E1BC]钢铁每小时产量增加:[-][00FF00]+3%[-]" />
	<configure id="[F1E1BC]稀矿每小时产量增加[-][00FF00]+3%[-]" value="[F1E1BC]稀矿每小时产量增加[-][00FF00]+3%[-]" />
	<configure id="[F1E1BC]石油每小时产量增加:[-][00FF00]+4%[-]" value="[F1E1BC]石油每小时产量增加:[-][00FF00]+4%[-]" />
	<configure id="[F1E1BC]金币每小时产量增加:[-][00FF00]+4%[-]" value="[F1E1BC]金币每小时产量增加:[-][00FF00]+4%[-]" />
	<configure id="[F1E1BC]钢铁每小时产量增加:[-][00FF00]+4%[-]" value="[F1E1BC]钢铁每小时产量增加:[-][00FF00]+4%[-]" />
	<configure id="[F1E1BC]稀矿每小时产量增加[-][00FF00]+4%[-]" value="[F1E1BC]稀矿每小时产量增加[-][00FF00]+4%[-]" />
	<configure id="[F1E1BC]石油每小时产量增加:[-][00FF00]+5%[-]" value="[F1E1BC]石油每小时产量增加:[-][00FF00]+5%[-]" />
	<configure id="[F1E1BC]金币每小时产量增加:[-][00FF00]+5%[-]" value="[F1E1BC]金币每小时产量增加:[-][00FF00]+5%[-]" />
	<configure id="[F1E1BC]钢铁每小时产量增加:[-][00FF00]+5%[-]" value="[F1E1BC]钢铁每小时产量增加:[-][00FF00]+5%[-]" />
	<configure id="[F1E1BC]稀矿每小时产量增加[-][00FF00]+5%[-]" value="[F1E1BC]稀矿每小时产量增加[-][00FF00]+5%[-]" />
	<configure id="[F1E1BC]石油每小时产量增加:[-][00FF00]+6%[-]" value="[F1E1BC]石油每小时产量增加:[-][00FF00]+6%[-]" />
	<configure id="[F1E1BC]金币每小时产量增加:[-][00FF00]+6%[-]" value="[F1E1BC]金币每小时产量增加:[-][00FF00]+6%[-]" />
	<configure id="[F1E1BC]钢铁每小时产量增加:[-][00FF00]+6%[-]" value="[F1E1BC]钢铁每小时产量增加:[-][00FF00]+6%[-]" />
	<configure id="[F1E1BC]稀矿每小时产量增加[-][00FF00]+6%[-]" value="[F1E1BC]稀矿每小时产量增加[-][00FF00]+6%[-]" />
	<configure id="[F1E1BC]石油每小时产量增加:[-][00FF00]+7%[-]" value="[F1E1BC]石油每小时产量增加:[-][00FF00]+7%[-]" />
	<configure id="[F1E1BC]金币每小时产量增加:[-][00FF00]+7%[-]" value="[F1E1BC]金币每小时产量增加:[-][00FF00]+7%[-]" />
	<configure id="[F1E1BC]钢铁每小时产量增加:[-][00FF00]+7%[-]" value="[F1E1BC]钢铁每小时产量增加:[-][00FF00]+7%[-]" />
	<configure id="[F1E1BC]稀矿每小时产量增加[-][00FF00]+7%[-]" value="[F1E1BC]稀矿每小时产量增加[-][00FF00]+7%[-]" />
	<configure id="[F1E1BC]石油每小时产量增加:[-][00FF00]+8%[-]" value="[F1E1BC]石油每小时产量增加:[-][00FF00]+8%[-]" />
	<configure id="[F1E1BC]金币每小时产量增加:[-][00FF00]+8%[-]" value="[F1E1BC]金币每小时产量增加:[-][00FF00]+8%[-]" />
	<configure id="[F1E1BC]钢铁每小时产量增加:[-][00FF00]+8%[-]" value="[F1E1BC]钢铁每小时产量增加:[-][00FF00]+8%[-]" />
	<configure id="[F1E1BC]稀矿每小时产量增加[-][00FF00]+8%[-]" value="[F1E1BC]稀矿每小时产量增加[-][00FF00]+8%[-]" />
	<configure id="[F1E1BC]所有建筑生命值提升[-][00FF00]+1%[-]" value="[F1E1BC]所有建筑生命值提升[-][00FF00]+1%[-]" />
	<configure id="[F1E1BC]所有防御塔攻击力提升:[-][00FF00]+1%[-]" value="[F1E1BC]所有防御塔攻击力提升:[-][00FF00]+1%[-]" />
	<configure id="[F1E1BC]所有兵种攻击力提升:[-][00FF00]+1%[-]" value="[F1E1BC]所有兵种攻击力提升:[-][00FF00]+1%[-]" />
	<configure id="[F1E1BC]所有兵种生命值提升:[-][00FF00]+1%[-]" value="[F1E1BC]所有兵种生命值提升:[-][00FF00]+1%[-]" />
	<configure id="[F1E1BC]资源掠夺保护增加:[-][00FF00]+1%[-]" value="[F1E1BC]资源掠夺保护增加:[-][00FF00]+1%[-]" />
	<configure id="[F1E1BC]所有建筑生命值提升[-][00FF00]+2%[-]" value="[F1E1BC]所有建筑生命值提升[-][00FF00]+2%[-]" />
	<configure id="[F1E1BC]所有防御塔攻击力提升:[-][00FF00]+2%[-]" value="[F1E1BC]所有防御塔攻击力提升:[-][00FF00]+2%[-]" />
	<configure id="[F1E1BC]所有兵种攻击力提升:[-][00FF00]+2%[-]" value="[F1E1BC]所有兵种攻击力提升:[-][00FF00]+2%[-]" />
	<configure id="[F1E1BC]所有兵种生命值提升:[-][00FF00]+2%[-]" value="[F1E1BC]所有兵种生命值提升:[-][00FF00]+2%[-]" />
	<configure id="[F1E1BC]资源掠夺保护增加:[-][00FF00]+2%[-]" value="[F1E1BC]资源掠夺保护增加:[-][00FF00]+2%[-]" />
	<configure id="[F1E1BC]所有建筑生命值提升[-][00FF00]+3%[-]" value="[F1E1BC]所有建筑生命值提升[-][00FF00]+3%[-]" />
	<configure id="[F1E1BC]所有防御塔攻击力提升:[-][00FF00]+3%[-]" value="[F1E1BC]所有防御塔攻击力提升:[-][00FF00]+3%[-]" />
	<configure id="[F1E1BC]所有兵种攻击力提升:[-][00FF00]+3%[-]" value="[F1E1BC]所有兵种攻击力提升:[-][00FF00]+3%[-]" />
	<configure id="[F1E1BC]所有兵种生命值提升:[-][00FF00]+3%[-]" value="[F1E1BC]所有兵种生命值提升:[-][00FF00]+3%[-]" />
	<configure id="[F1E1BC]资源掠夺保护增加:[-][00FF00]+3%[-]" value="[F1E1BC]资源掠夺保护增加:[-][00FF00]+3%[-]" />
	<configure id="[F1E1BC]所有建筑生命值提升[-][00FF00]+4%[-]" value="[F1E1BC]所有建筑生命值提升[-][00FF00]+4%[-]" />
	<configure id="[F1E1BC]所有防御塔攻击力提升:[-][00FF00]+4%[-]" value="[F1E1BC]所有防御塔攻击力提升:[-][00FF00]+4%[-]" />
	<configure id="[F1E1BC]所有兵种攻击力提升:[-][00FF00]+4%[-]" value="[F1E1BC]所有兵种攻击力提升:[-][00FF00]+4%[-]" />
	<configure id="[F1E1BC]所有兵种生命值提升:[-][00FF00]+4%[-]" value="[F1E1BC]所有兵种生命值提升:[-][00FF00]+4%[-]" />
	<configure id="[F1E1BC]资源掠夺保护增加:[-][00FF00]+4%[-]" value="[F1E1BC]资源掠夺保护增加:[-][00FF00]+4%[-]" />
	<configure id="[F1E1BC]所有建筑生命值提升[-][00FF00]+5%[-]" value="[F1E1BC]所有建筑生命值提升[-][00FF00]+5%[-]" />
	<configure id="[F1E1BC]所有防御塔攻击力提升:[-][00FF00]+5%[-]" value="[F1E1BC]所有防御塔攻击力提升:[-][00FF00]+5%[-]" />
	<configure id="[F1E1BC]所有兵种攻击力提升:[-][00FF00]+5%[-]" value="[F1E1BC]所有兵种攻击力提升:[-][00FF00]+5%[-]" />
	<configure id="[F1E1BC]所有兵种生命值提升:[-][00FF00]+5%[-]" value="[F1E1BC]所有兵种生命值提升:[-][00FF00]+5%[-]" />
	<configure id="[F1E1BC]资源掠夺保护增加:[-][00FF00]+5%[-]" value="[F1E1BC]资源掠夺保护增加:[-][00FF00]+5%[-]" />
	<configure id="[F1E1BC]所有建筑生命值提升[-][00FF00]+8%[-]" value="[F1E1BC]所有建筑生命值提升[-][00FF00]+8%[-]" />
	<configure id="[F1E1BC]所有防御塔攻击力提升:[-][00FF00]+8%[-]" value="[F1E1BC]所有防御塔攻击力提升:[-][00FF00]+8%[-]" />
	<configure id="[F1E1BC]所有兵种攻击力提升:[-][00FF00]+8%[-]" value="[F1E1BC]所有兵种攻击力提升:[-][00FF00]+8%[-]" />
	<configure id="[F1E1BC]所有兵种生命值提升:[-][00FF00]+8%[-]" value="[F1E1BC]所有兵种生命值提升:[-][00FF00]+8%[-]" />
	<configure id="[F1E1BC]资源掠夺保护增加:[-][00FF00]+8%[-]" value="[F1E1BC]资源掠夺保护增加:[-][00FF00]+8%[-]" />
	<configure id="[F1E1BC]所有建筑生命值提升[-][00FF00]+10%[-]" value="[F1E1BC]所有建筑生命值提升[-][00FF00]+10%[-]" />
	<configure id="[F1E1BC]所有防御塔攻击力提升:[-][00FF00]+10%[-]" value="[F1E1BC]所有防御塔攻击力提升:[-][00FF00]+10%[-]" />
	<configure id="[F1E1BC]所有兵种攻击力提升:[-][00FF00]+10%[-]" value="[F1E1BC]所有兵种攻击力提升:[-][00FF00]+10%[-]" />
	<configure id="[F1E1BC]所有兵种生命值提升:[-][00FF00]+10%[-]" value="[F1E1BC]所有兵种生命值提升:[-][00FF00]+10%[-]" />
	<configure id="[F1E1BC]资源掠夺保护增加:[-][00FF00]+10%[-]" value="[F1E1BC]资源掠夺保护增加:[-][00FF00]+10%[-]" />
	<configure id="特权" value="特权" />
	<configure id="尊享" value="尊享" />
	<configure id="充值" value="充值" />
	<configure id="即可升级到" value="即可升级到" />
	<configure id="月卡" value="月卡" />
	<configure id="购买" value="购买" />
	<configure id="续费" value="续费" />
	<configure id="购买即可获得" value="购买即可获得" />
	<configure id="每日领取" value="每日领取" />
	<configure id="30天期限" value="30天期限" />
	<configure id="有效期至：无限期" value="有效期至：无限期" />
	<configure id="无期限" value="无期限" />
	<configure id="有效期至" value="有效期至" />
	<configure id="元" value="元" />
</configures>