<?xml version="1.0" encoding="UTF-8" standalone="yes"?>
<configures>
	<configure terrainIdx="1" pos="142" idx="28" lv="1" islandType="1" />
	<configure terrainIdx="1" pos="147" idx="28" lv="1" islandType="1" />
	<configure terrainIdx="1" pos="152" idx="28" lv="1" islandType="1" />
	<configure terrainIdx="1" pos="157" idx="28" lv="1" islandType="1" />
	<configure terrainIdx="1" pos="162" idx="28" lv="1" islandType="1" />
	<configure terrainIdx="1" pos="167" idx="28" lv="1" islandType="1" />
	<configure terrainIdx="1" pos="177" idx="28" lv="1" islandType="1" />
	<configure terrainIdx="1" pos="182" idx="28" lv="1" islandType="1" />
	<configure terrainIdx="1" pos="187" idx="28" lv="1" islandType="1" />
	<configure terrainIdx="1" pos="192" idx="28" lv="1" islandType="1" />
	<configure terrainIdx="1" pos="197" idx="28" lv="1" islandType="1" />
	<configure terrainIdx="1" pos="202" idx="28" lv="1" islandType="1" />
	<configure terrainIdx="1" pos="207" idx="28" lv="1" islandType="1" />
	<configure terrainIdx="1" pos="492" idx="28" lv="1" islandType="1" />
	<configure terrainIdx="1" pos="497" idx="28" lv="1" islandType="1" />
	<configure terrainIdx="1" pos="502" idx="28" lv="1" islandType="1" />
	<configure terrainIdx="1" pos="507" idx="28" lv="1" islandType="1" />
	<configure terrainIdx="1" pos="517" idx="28" lv="1" islandType="1" />
	<configure terrainIdx="1" pos="522" idx="28" lv="1" islandType="1" />
	<configure terrainIdx="1" pos="527" idx="28" lv="1" islandType="1" />
	<configure terrainIdx="1" pos="537" idx="28" lv="1" islandType="1" />
	<configure terrainIdx="1" pos="542" idx="28" lv="1" islandType="1" />
	<configure terrainIdx="1" pos="547" idx="28" lv="1" islandType="1" />
	<configure terrainIdx="1" pos="552" idx="28" lv="1" islandType="1" />
	<configure terrainIdx="1" pos="557" idx="28" lv="1" islandType="1" />
	<configure terrainIdx="1" pos="842" idx="28" lv="1" islandType="1" />
	<configure terrainIdx="1" pos="847" idx="28" lv="1" islandType="1" />
	<configure terrainIdx="1" pos="1192" idx="28" lv="1" islandType="1" />
	<configure terrainIdx="1" pos="1542" idx="28" lv="1" islandType="1" />
	<configure terrainIdx="1" pos="1547" idx="28" lv="1" islandType="1" />
	<configure terrainIdx="1" pos="1892" idx="28" lv="1" islandType="1" />
	<configure terrainIdx="1" pos="1897" idx="28" lv="1" islandType="1" />
	<configure terrainIdx="1" pos="2242" idx="28" lv="1" islandType="1" />
	<configure terrainIdx="1" pos="2592" idx="28" lv="1" islandType="1" />
	<configure terrainIdx="1" pos="2597" idx="28" lv="1" islandType="1" />
	<configure terrainIdx="1" pos="2947" idx="28" lv="1" islandType="1" />
	<configure terrainIdx="1" pos="3292" idx="28" lv="1" islandType="1" />
	<configure terrainIdx="1" pos="3297" idx="28" lv="1" islandType="1" />
	<configure terrainIdx="1" pos="3647" idx="28" lv="1" islandType="1" />
	<configure terrainIdx="1" pos="3992" idx="28" lv="1" islandType="1" />
	<configure terrainIdx="1" pos="3997" idx="28" lv="1" islandType="1" />
	<configure terrainIdx="1" pos="4342" idx="28" lv="1" islandType="1" />
	<configure terrainIdx="1" pos="4692" idx="28" lv="1" islandType="1" />
	<configure terrainIdx="1" pos="4697" idx="28" lv="1" islandType="1" />
	<configure terrainIdx="1" pos="103" idx="31" lv="1" islandType="1" />
	<configure terrainIdx="1" pos="123" idx="31" lv="1" islandType="1" />
	<configure terrainIdx="1" pos="443" idx="31" lv="1" islandType="1" />
	<configure terrainIdx="1" pos="786" idx="31" lv="1" islandType="1" />
	<configure terrainIdx="1" pos="1350" idx="31" lv="1" islandType="1" />
	<configure terrainIdx="1" pos="802" idx="31" lv="1" islandType="1" />
	<configure terrainIdx="1" pos="1622" idx="31" lv="1" islandType="1" />
	<configure terrainIdx="1" pos="1128" idx="31" lv="1" islandType="1" />
	<configure terrainIdx="1" pos="2178" idx="31" lv="1" islandType="1" />
	<configure terrainIdx="1" pos="2873" idx="31" lv="1" islandType="1" />
	<configure terrainIdx="1" pos="3206" idx="31" lv="1" islandType="1" />
	<configure terrainIdx="1" pos="3573" idx="31" lv="1" islandType="1" />
	<configure terrainIdx="1" pos="3582" idx="31" lv="1" islandType="1" />
	<configure terrainIdx="1" pos="4278" idx="31" lv="1" islandType="1" />
	<configure terrainIdx="1" pos="463" idx="31" lv="1" islandType="1" />
	<configure terrainIdx="1" pos="1094" idx="31" lv="1" islandType="1" />
	<configure terrainIdx="1" pos="826" idx="31" lv="1" islandType="1" />
	<configure terrainIdx="1" pos="834" idx="31" lv="1" islandType="1" />
	<configure terrainIdx="1" pos="1781" idx="31" lv="1" islandType="1" />
	<configure terrainIdx="1" pos="851" idx="26" lv="1" islandType="1" />
	<configure terrainIdx="1" pos="859" idx="26" lv="1" islandType="1" />
	<configure terrainIdx="1" pos="863" idx="26" lv="1" islandType="1" />
	<configure terrainIdx="1" pos="867" idx="26" lv="1" islandType="1" />
	<configure terrainIdx="1" pos="875" idx="26" lv="1" islandType="1" />
	<configure terrainIdx="1" pos="1131" idx="26" lv="1" islandType="1" />
	<configure terrainIdx="1" pos="1135" idx="26" lv="1" islandType="1" />
	<configure terrainIdx="1" pos="1139" idx="26" lv="1" islandType="1" />
	<configure terrainIdx="1" pos="1143" idx="26" lv="1" islandType="1" />
	<configure terrainIdx="1" pos="1147" idx="26" lv="1" islandType="1" />
	<configure terrainIdx="1" pos="1151" idx="26" lv="1" islandType="1" />
	<configure terrainIdx="1" pos="1155" idx="26" lv="1" islandType="1" />
	<configure terrainIdx="1" pos="1411" idx="26" lv="1" islandType="1" />
	<configure terrainIdx="1" pos="1415" idx="26" lv="1" islandType="1" />
	<configure terrainIdx="1" pos="1423" idx="26" lv="1" islandType="1" />
	<configure terrainIdx="1" pos="1427" idx="26" lv="1" islandType="1" />
	<configure terrainIdx="1" pos="1695" idx="26" lv="1" islandType="1" />
	<configure terrainIdx="1" pos="1699" idx="26" lv="1" islandType="1" />
	<configure terrainIdx="1" pos="1703" idx="26" lv="1" islandType="1" />
	<configure terrainIdx="1" pos="1971" idx="26" lv="1" islandType="1" />
	<configure terrainIdx="1" pos="1975" idx="26" lv="1" islandType="1" />
	<configure terrainIdx="1" pos="1979" idx="26" lv="1" islandType="1" />
	<configure terrainIdx="1" pos="2251" idx="26" lv="1" islandType="1" />
	<configure terrainIdx="1" pos="2255" idx="26" lv="1" islandType="1" />
	<configure terrainIdx="1" pos="2531" idx="26" lv="1" islandType="1" />
	<configure terrainIdx="1" pos="2535" idx="26" lv="1" islandType="1" />
	<configure terrainIdx="1" pos="2811" idx="26" lv="1" islandType="1" />
	<configure terrainIdx="1" pos="2815" idx="26" lv="1" islandType="1" />
	<configure terrainIdx="1" pos="3091" idx="26" lv="1" islandType="1" />
	<configure terrainIdx="1" pos="3371" idx="26" lv="1" islandType="1" />
	<configure terrainIdx="1" pos="3375" idx="26" lv="1" islandType="1" />
	<configure terrainIdx="1" pos="3655" idx="26" lv="1" islandType="1" />
	<configure terrainIdx="1" pos="3931" idx="26" lv="1" islandType="1" />
	<configure terrainIdx="1" pos="3935" idx="26" lv="1" islandType="1" />
	<configure terrainIdx="1" pos="4211" idx="26" lv="1" islandType="1" />
	<configure terrainIdx="1" pos="4215" idx="26" lv="1" islandType="1" />
	<configure terrainIdx="1" pos="4491" idx="26" lv="1" islandType="1" />
	<configure terrainIdx="1" pos="4495" idx="26" lv="1" islandType="1" />
	<configure terrainIdx="1" pos="4771" idx="26" lv="1" islandType="1" />
	<configure terrainIdx="1" pos="1799" idx="26" lv="1" islandType="1" />
	<configure terrainIdx="1" pos="2506" idx="26" lv="1" islandType="1" />
	<configure terrainIdx="1" pos="3733" idx="26" lv="1" islandType="1" />
	<configure terrainIdx="1" pos="2271" idx="1" lv="1" islandType="1" />
	<configure terrainIdx="1" pos="2620" idx="2" lv="1" islandType="1" />
	<configure terrainIdx="1" pos="2896" idx="3" lv="1" islandType="1" />
	<configure terrainIdx="1" pos="2624" idx="6" lv="1" islandType="1" />
	<configure terrainIdx="1" pos="2628" idx="6" lv="1" islandType="1" />
	<configure terrainIdx="1" pos="2974" idx="7" lv="1" islandType="1" />
	<configure terrainIdx="1" pos="2281" idx="10" lv="1" islandType="1" />
	<configure terrainIdx="1" pos="4800" idx="15" lv="1" islandType="1" />
	<configure terrainIdx="1" pos="4313" idx="15" lv="1" islandType="1" />
	<configure terrainIdx="1" pos="10000" idx="13" lv="1" islandType="1" />
	<configure terrainIdx="1" pos="10001" idx="12" lv="1" islandType="1" />
	<configure terrainIdx="1" pos="10002" idx="12" lv="1" islandType="1" />
	<configure terrainIdx="1" pos="10003" idx="12" lv="1" islandType="1" />
	<configure terrainIdx="1" pos="10004" idx="12" lv="1" islandType="1" />
	<configure terrainIdx="1" pos="10005" idx="12" lv="1" islandType="1" />
	<configure terrainIdx="2" pos="315" idx="1" lv="10" islandType="6" />
	<configure terrainIdx="2" pos="287" idx="2" lv="10" islandType="6" />
	<configure terrainIdx="2" pos="339" idx="3" lv="10" islandType="6" />
	<configure terrainIdx="2" pos="917" idx="4" lv="10" islandType="6" />
	<configure terrainIdx="2" pos="1182" idx="5" lv="10" islandType="6" />
	<configure terrainIdx="2" pos="1345" idx="6" lv="10" islandType="6" />
	<configure terrainIdx="2" pos="1383" idx="6" lv="10" islandType="6" />
	<configure terrainIdx="2" pos="1772" idx="9" lv="10" islandType="6" />
	<configure terrainIdx="2" pos="1784" idx="10" lv="10" islandType="6" />
	<configure terrainIdx="2" pos="1794" idx="11" lv="10" islandType="6" />
	<configure terrainIdx="2" pos="3041" idx="14" lv="1" islandType="6" />
	<configure terrainIdx="2" pos="309" idx="16" lv="20" islandType="6" />
	<configure terrainIdx="2" pos="321" idx="16" lv="20" islandType="6" />
	<configure terrainIdx="2" pos="1294" idx="16" lv="20" islandType="6" />
	<configure terrainIdx="2" pos="730" idx="19" lv="20" islandType="6" />
	<configure terrainIdx="2" pos="740" idx="19" lv="20" islandType="6" />
	<configure terrainIdx="2" pos="2268" idx="17" lv="20" islandType="6" />
	<configure terrainIdx="2" pos="2280" idx="17" lv="20" islandType="6" />
	<configure terrainIdx="2" pos="2694" idx="17" lv="20" islandType="6" />
	<configure terrainIdx="2" pos="2707" idx="17" lv="20" islandType="6" />
	<configure terrainIdx="2" pos="1282" idx="15" lv="20" islandType="6" />
	<configure terrainIdx="2" pos="1306" idx="15" lv="20" islandType="6" />
	<configure terrainIdx="2" pos="1835" idx="15" lv="20" islandType="6" />
	<configure terrainIdx="2" pos="1874" idx="15" lv="20" islandType="6" />
	<configure terrainIdx="2" pos="2292" idx="15" lv="20" islandType="6" />
	<configure terrainIdx="2" pos="2682" idx="15" lv="20" islandType="6" />
	<configure terrainIdx="2" pos="303" idx="18" lv="20" islandType="6" />
	<configure terrainIdx="2" pos="327" idx="18" lv="20" islandType="6" />
	<configure terrainIdx="2" pos="2668" idx="18" lv="20" islandType="6" />
	<configure terrainIdx="2" pos="2719" idx="15" lv="20" islandType="6" />
	<configure terrainIdx="2" pos="717" idx="15" lv="20" islandType="6" />
	<configure terrainIdx="2" pos="752" idx="15" lv="20" islandType="6" />
	<configure terrainIdx="2" pos="724" idx="17" lv="20" islandType="6" />
	<configure terrainIdx="2" pos="746" idx="17" lv="20" islandType="6" />
	<configure terrainIdx="2" pos="10000" idx="13" lv="1" islandType="6" />
	<configure terrainIdx="2" pos="10001" idx="12" lv="1" islandType="6" />
	<configure terrainIdx="2" pos="10002" idx="12" lv="1" islandType="6" />
	<configure terrainIdx="2" pos="10003" idx="12" lv="1" islandType="6" />
	<configure terrainIdx="2" pos="10004" idx="12" lv="1" islandType="6" />
	<configure terrainIdx="2" pos="10005" idx="12" lv="1" islandType="6" />
	<configure terrainIdx="3" pos="142" idx="28" lv="1" islandType="6" />
	<configure terrainIdx="3" pos="147" idx="28" lv="1" islandType="6" />
	<configure terrainIdx="3" pos="152" idx="28" lv="1" islandType="6" />
	<configure terrainIdx="3" pos="157" idx="28" lv="1" islandType="6" />
	<configure terrainIdx="3" pos="162" idx="28" lv="1" islandType="6" />
	<configure terrainIdx="3" pos="167" idx="28" lv="1" islandType="6" />
	<configure terrainIdx="3" pos="177" idx="28" lv="1" islandType="6" />
	<configure terrainIdx="3" pos="182" idx="28" lv="1" islandType="6" />
	<configure terrainIdx="3" pos="187" idx="28" lv="1" islandType="6" />
	<configure terrainIdx="3" pos="192" idx="28" lv="1" islandType="6" />
	<configure terrainIdx="3" pos="197" idx="28" lv="1" islandType="6" />
	<configure terrainIdx="3" pos="202" idx="28" lv="1" islandType="6" />
	<configure terrainIdx="3" pos="207" idx="28" lv="1" islandType="6" />
	<configure terrainIdx="3" pos="492" idx="28" lv="1" islandType="6" />
	<configure terrainIdx="3" pos="497" idx="28" lv="1" islandType="6" />
	<configure terrainIdx="3" pos="502" idx="28" lv="1" islandType="6" />
	<configure terrainIdx="3" pos="507" idx="28" lv="1" islandType="6" />
	<configure terrainIdx="3" pos="517" idx="28" lv="1" islandType="6" />
	<configure terrainIdx="3" pos="522" idx="28" lv="1" islandType="6" />
	<configure terrainIdx="3" pos="527" idx="28" lv="1" islandType="6" />
	<configure terrainIdx="3" pos="537" idx="28" lv="1" islandType="6" />
	<configure terrainIdx="3" pos="542" idx="28" lv="1" islandType="6" />
	<configure terrainIdx="3" pos="547" idx="28" lv="1" islandType="6" />
	<configure terrainIdx="3" pos="552" idx="28" lv="1" islandType="6" />
	<configure terrainIdx="3" pos="557" idx="28" lv="1" islandType="6" />
	<configure terrainIdx="3" pos="842" idx="28" lv="1" islandType="6" />
	<configure terrainIdx="3" pos="847" idx="28" lv="1" islandType="6" />
	<configure terrainIdx="3" pos="1192" idx="28" lv="1" islandType="6" />
	<configure terrainIdx="3" pos="1542" idx="28" lv="1" islandType="6" />
	<configure terrainIdx="3" pos="1547" idx="28" lv="1" islandType="6" />
	<configure terrainIdx="3" pos="1892" idx="28" lv="1" islandType="6" />
	<configure terrainIdx="3" pos="1897" idx="28" lv="1" islandType="6" />
	<configure terrainIdx="3" pos="2242" idx="28" lv="1" islandType="6" />
	<configure terrainIdx="3" pos="2592" idx="28" lv="1" islandType="6" />
	<configure terrainIdx="3" pos="2597" idx="28" lv="1" islandType="6" />
	<configure terrainIdx="3" pos="2947" idx="28" lv="1" islandType="6" />
	<configure terrainIdx="3" pos="3292" idx="28" lv="1" islandType="6" />
	<configure terrainIdx="3" pos="3297" idx="28" lv="1" islandType="6" />
	<configure terrainIdx="3" pos="3647" idx="28" lv="1" islandType="6" />
	<configure terrainIdx="3" pos="3992" idx="28" lv="1" islandType="6" />
	<configure terrainIdx="3" pos="3997" idx="28" lv="1" islandType="6" />
	<configure terrainIdx="3" pos="4342" idx="28" lv="1" islandType="6" />
	<configure terrainIdx="3" pos="4692" idx="28" lv="1" islandType="6" />
	<configure terrainIdx="3" pos="4697" idx="28" lv="1" islandType="6" />
	<configure terrainIdx="3" pos="103" idx="31" lv="1" islandType="6" />
	<configure terrainIdx="3" pos="123" idx="31" lv="1" islandType="6" />
	<configure terrainIdx="3" pos="443" idx="31" lv="1" islandType="6" />
	<configure terrainIdx="3" pos="786" idx="31" lv="1" islandType="6" />
	<configure terrainIdx="3" pos="1350" idx="31" lv="1" islandType="6" />
	<configure terrainIdx="3" pos="802" idx="31" lv="1" islandType="6" />
	<configure terrainIdx="3" pos="1622" idx="31" lv="1" islandType="6" />
	<configure terrainIdx="3" pos="1128" idx="31" lv="1" islandType="6" />
	<configure terrainIdx="3" pos="2178" idx="31" lv="1" islandType="6" />
	<configure terrainIdx="3" pos="2873" idx="31" lv="1" islandType="6" />
	<configure terrainIdx="3" pos="3206" idx="31" lv="1" islandType="6" />
	<configure terrainIdx="3" pos="3573" idx="31" lv="1" islandType="6" />
	<configure terrainIdx="3" pos="3582" idx="31" lv="1" islandType="6" />
	<configure terrainIdx="3" pos="4278" idx="31" lv="1" islandType="6" />
	<configure terrainIdx="3" pos="463" idx="31" lv="1" islandType="6" />
	<configure terrainIdx="3" pos="1094" idx="31" lv="1" islandType="6" />
	<configure terrainIdx="3" pos="826" idx="31" lv="1" islandType="6" />
	<configure terrainIdx="3" pos="834" idx="31" lv="1" islandType="6" />
	<configure terrainIdx="3" pos="1781" idx="31" lv="1" islandType="6" />
	<configure terrainIdx="3" pos="851" idx="26" lv="1" islandType="6" />
	<configure terrainIdx="3" pos="859" idx="26" lv="1" islandType="6" />
	<configure terrainIdx="3" pos="863" idx="26" lv="1" islandType="6" />
	<configure terrainIdx="3" pos="867" idx="26" lv="1" islandType="6" />
	<configure terrainIdx="3" pos="875" idx="26" lv="1" islandType="6" />
	<configure terrainIdx="3" pos="1131" idx="26" lv="1" islandType="6" />
	<configure terrainIdx="3" pos="1135" idx="26" lv="1" islandType="6" />
	<configure terrainIdx="3" pos="1139" idx="26" lv="1" islandType="6" />
	<configure terrainIdx="3" pos="1143" idx="26" lv="1" islandType="6" />
	<configure terrainIdx="3" pos="1147" idx="26" lv="1" islandType="6" />
	<configure terrainIdx="3" pos="1151" idx="26" lv="1" islandType="6" />
	<configure terrainIdx="3" pos="1155" idx="26" lv="1" islandType="6" />
	<configure terrainIdx="3" pos="1411" idx="26" lv="1" islandType="6" />
	<configure terrainIdx="3" pos="1415" idx="26" lv="1" islandType="6" />
	<configure terrainIdx="3" pos="1423" idx="26" lv="1" islandType="6" />
	<configure terrainIdx="3" pos="1427" idx="26" lv="1" islandType="6" />
	<configure terrainIdx="3" pos="1695" idx="26" lv="1" islandType="6" />
	<configure terrainIdx="3" pos="1699" idx="26" lv="1" islandType="6" />
	<configure terrainIdx="3" pos="1703" idx="26" lv="1" islandType="6" />
	<configure terrainIdx="3" pos="1971" idx="26" lv="1" islandType="6" />
	<configure terrainIdx="3" pos="1975" idx="26" lv="1" islandType="6" />
	<configure terrainIdx="3" pos="1979" idx="26" lv="1" islandType="6" />
	<configure terrainIdx="3" pos="2251" idx="26" lv="1" islandType="6" />
	<configure terrainIdx="3" pos="2255" idx="26" lv="1" islandType="6" />
	<configure terrainIdx="3" pos="2531" idx="26" lv="1" islandType="6" />
	<configure terrainIdx="3" pos="2535" idx="26" lv="1" islandType="6" />
	<configure terrainIdx="3" pos="2811" idx="26" lv="1" islandType="6" />
	<configure terrainIdx="3" pos="2815" idx="26" lv="1" islandType="6" />
	<configure terrainIdx="3" pos="3091" idx="26" lv="1" islandType="6" />
	<configure terrainIdx="3" pos="3371" idx="26" lv="1" islandType="6" />
	<configure terrainIdx="3" pos="3375" idx="26" lv="1" islandType="6" />
	<configure terrainIdx="3" pos="3655" idx="26" lv="1" islandType="6" />
	<configure terrainIdx="3" pos="3931" idx="26" lv="1" islandType="6" />
	<configure terrainIdx="3" pos="3935" idx="26" lv="1" islandType="6" />
	<configure terrainIdx="3" pos="4211" idx="26" lv="1" islandType="6" />
	<configure terrainIdx="3" pos="4215" idx="26" lv="1" islandType="6" />
	<configure terrainIdx="3" pos="4491" idx="26" lv="1" islandType="6" />
	<configure terrainIdx="3" pos="4495" idx="26" lv="1" islandType="6" />
	<configure terrainIdx="3" pos="4771" idx="26" lv="1" islandType="6" />
	<configure terrainIdx="3" pos="1799" idx="26" lv="1" islandType="6" />
	<configure terrainIdx="3" pos="2506" idx="26" lv="1" islandType="6" />
	<configure terrainIdx="3" pos="3733" idx="26" lv="1" islandType="6" />
	<configure terrainIdx="3" pos="2271" idx="1" lv="15" islandType="6" />
	<configure terrainIdx="3" pos="2620" idx="2" lv="15" islandType="6" />
	<configure terrainIdx="3" pos="2616" idx="2" lv="15" islandType="6" />
	<configure terrainIdx="3" pos="2896" idx="3" lv="15" islandType="6" />
	<configure terrainIdx="3" pos="2900" idx="3" lv="15" islandType="6" />
	<configure terrainIdx="3" pos="3176" idx="4" lv="15" islandType="6" />
	<configure terrainIdx="3" pos="3180" idx="4" lv="15" islandType="6" />
	<configure terrainIdx="3" pos="3456" idx="5" lv="15" islandType="6" />
	<configure terrainIdx="3" pos="3460" idx="5" lv="15" islandType="6" />
	<configure terrainIdx="3" pos="2624" idx="6" lv="15" islandType="6" />
	<configure terrainIdx="3" pos="2628" idx="6" lv="15" islandType="6" />
	<configure terrainIdx="3" pos="2632" idx="6" lv="15" islandType="6" />
	<configure terrainIdx="3" pos="2636" idx="6" lv="15" islandType="6" />
	<configure terrainIdx="3" pos="2974" idx="7" lv="15" islandType="6" />
	<configure terrainIdx="3" pos="2979" idx="8" lv="15" islandType="6" />
	<configure terrainIdx="3" pos="3324" idx="9" lv="15" islandType="6" />
	<configure terrainIdx="3" pos="2281" idx="10" lv="15" islandType="6" />
	<configure terrainIdx="3" pos="2206" idx="11" lv="15" islandType="6" />
	<configure terrainIdx="3" pos="2276" idx="14" lv="1" islandType="6" />
	<configure terrainIdx="3" pos="2610" idx="16" lv="20" islandType="6" />
	<configure terrainIdx="3" pos="2195" idx="16" lv="20" islandType="6" />
	<configure terrainIdx="3" pos="1791" idx="16" lv="20" islandType="6" />
	<configure terrainIdx="3" pos="3812" idx="19" lv="20" islandType="6" />
	<configure terrainIdx="3" pos="3606" idx="19" lv="20" islandType="6" />
	<configure terrainIdx="3" pos="4303" idx="19" lv="20" islandType="6" />
	<configure terrainIdx="3" pos="4207" idx="17" lv="20" islandType="6" />
	<configure terrainIdx="3" pos="3750" idx="17" lv="20" islandType="6" />
	<configure terrainIdx="3" pos="3544" idx="17" lv="20" islandType="6" />
	<configure terrainIdx="3" pos="4800" idx="17" lv="20" islandType="6" />
	<configure terrainIdx="3" pos="3897" idx="15" lv="20" islandType="6" />
	<configure terrainIdx="3" pos="3622" idx="15" lv="20" islandType="6" />
	<configure terrainIdx="3" pos="3626" idx="15" lv="20" islandType="6" />
	<configure terrainIdx="3" pos="3630" idx="15" lv="20" islandType="6" />
	<configure terrainIdx="3" pos="3270" idx="15" lv="20" islandType="6" />
	<configure terrainIdx="3" pos="3280" idx="18" lv="20" islandType="6" />
	<configure terrainIdx="3" pos="3284" idx="18" lv="20" islandType="6" />
	<configure terrainIdx="3" pos="10000" idx="13" lv="1" islandType="6" />
	<configure terrainIdx="3" pos="10001" idx="12" lv="1" islandType="6" />
	<configure terrainIdx="3" pos="10002" idx="12" lv="1" islandType="6" />
	<configure terrainIdx="3" pos="10003" idx="12" lv="1" islandType="6" />
	<configure terrainIdx="3" pos="10004" idx="12" lv="1" islandType="6" />
	<configure terrainIdx="3" pos="10005" idx="12" lv="1" islandType="6" />
	<configure terrainIdx="4" pos="142" idx="18" lv="1" islandType="6" />
	<configure terrainIdx="4" pos="147" idx="28" lv="1" islandType="6" />
	<configure terrainIdx="4" pos="152" idx="28" lv="1" islandType="6" />
	<configure terrainIdx="4" pos="157" idx="28" lv="1" islandType="6" />
	<configure terrainIdx="4" pos="162" idx="28" lv="1" islandType="6" />
	<configure terrainIdx="4" pos="167" idx="28" lv="1" islandType="6" />
	<configure terrainIdx="4" pos="177" idx="28" lv="1" islandType="6" />
	<configure terrainIdx="4" pos="182" idx="28" lv="1" islandType="6" />
	<configure terrainIdx="4" pos="187" idx="28" lv="1" islandType="6" />
	<configure terrainIdx="4" pos="192" idx="28" lv="1" islandType="6" />
	<configure terrainIdx="4" pos="197" idx="28" lv="1" islandType="6" />
	<configure terrainIdx="4" pos="202" idx="28" lv="1" islandType="6" />
	<configure terrainIdx="4" pos="207" idx="28" lv="1" islandType="6" />
	<configure terrainIdx="4" pos="492" idx="28" lv="1" islandType="6" />
	<configure terrainIdx="4" pos="497" idx="28" lv="1" islandType="6" />
	<configure terrainIdx="4" pos="502" idx="28" lv="1" islandType="6" />
	<configure terrainIdx="4" pos="507" idx="28" lv="1" islandType="6" />
	<configure terrainIdx="4" pos="517" idx="28" lv="1" islandType="6" />
	<configure terrainIdx="4" pos="522" idx="28" lv="1" islandType="6" />
	<configure terrainIdx="4" pos="527" idx="28" lv="1" islandType="6" />
	<configure terrainIdx="4" pos="537" idx="28" lv="1" islandType="6" />
	<configure terrainIdx="4" pos="542" idx="28" lv="1" islandType="6" />
	<configure terrainIdx="4" pos="547" idx="28" lv="1" islandType="6" />
	<configure terrainIdx="4" pos="552" idx="28" lv="1" islandType="6" />
	<configure terrainIdx="4" pos="557" idx="28" lv="1" islandType="6" />
	<configure terrainIdx="4" pos="842" idx="28" lv="1" islandType="6" />
	<configure terrainIdx="4" pos="847" idx="28" lv="1" islandType="6" />
	<configure terrainIdx="4" pos="1192" idx="28" lv="1" islandType="6" />
	<configure terrainIdx="4" pos="1542" idx="28" lv="1" islandType="6" />
	<configure terrainIdx="4" pos="1547" idx="28" lv="1" islandType="6" />
	<configure terrainIdx="4" pos="1892" idx="28" lv="1" islandType="6" />
	<configure terrainIdx="4" pos="1897" idx="28" lv="1" islandType="6" />
	<configure terrainIdx="4" pos="2242" idx="28" lv="1" islandType="6" />
	<configure terrainIdx="4" pos="2592" idx="28" lv="1" islandType="6" />
	<configure terrainIdx="4" pos="2597" idx="28" lv="1" islandType="6" />
	<configure terrainIdx="4" pos="2947" idx="28" lv="1" islandType="6" />
	<configure terrainIdx="4" pos="3292" idx="28" lv="1" islandType="6" />
	<configure terrainIdx="4" pos="3297" idx="28" lv="1" islandType="6" />
	<configure terrainIdx="4" pos="3647" idx="28" lv="1" islandType="6" />
	<configure terrainIdx="4" pos="3992" idx="28" lv="1" islandType="6" />
	<configure terrainIdx="4" pos="3997" idx="28" lv="1" islandType="6" />
	<configure terrainIdx="4" pos="4342" idx="28" lv="1" islandType="6" />
	<configure terrainIdx="4" pos="4692" idx="28" lv="1" islandType="6" />
	<configure terrainIdx="4" pos="4697" idx="28" lv="1" islandType="6" />
	<configure terrainIdx="4" pos="103" idx="31" lv="1" islandType="6" />
	<configure terrainIdx="4" pos="123" idx="31" lv="1" islandType="6" />
	<configure terrainIdx="4" pos="443" idx="31" lv="1" islandType="6" />
	<configure terrainIdx="4" pos="786" idx="31" lv="1" islandType="6" />
	<configure terrainIdx="4" pos="1350" idx="31" lv="1" islandType="6" />
	<configure terrainIdx="4" pos="802" idx="31" lv="1" islandType="6" />
	<configure terrainIdx="4" pos="1622" idx="31" lv="1" islandType="6" />
	<configure terrainIdx="4" pos="1128" idx="31" lv="1" islandType="6" />
	<configure terrainIdx="4" pos="2178" idx="31" lv="1" islandType="6" />
	<configure terrainIdx="4" pos="2873" idx="31" lv="1" islandType="6" />
	<configure terrainIdx="4" pos="3206" idx="31" lv="1" islandType="6" />
	<configure terrainIdx="4" pos="3573" idx="31" lv="1" islandType="6" />
	<configure terrainIdx="4" pos="3582" idx="31" lv="1" islandType="6" />
	<configure terrainIdx="4" pos="4278" idx="31" lv="1" islandType="6" />
	<configure terrainIdx="4" pos="463" idx="31" lv="1" islandType="6" />
	<configure terrainIdx="4" pos="1094" idx="31" lv="1" islandType="6" />
	<configure terrainIdx="4" pos="826" idx="31" lv="1" islandType="6" />
	<configure terrainIdx="4" pos="834" idx="31" lv="1" islandType="6" />
	<configure terrainIdx="4" pos="1781" idx="31" lv="1" islandType="6" />
	<configure terrainIdx="4" pos="851" idx="26" lv="1" islandType="6" />
	<configure terrainIdx="4" pos="859" idx="26" lv="1" islandType="6" />
	<configure terrainIdx="4" pos="863" idx="26" lv="1" islandType="6" />
	<configure terrainIdx="4" pos="867" idx="26" lv="1" islandType="6" />
	<configure terrainIdx="4" pos="875" idx="26" lv="1" islandType="6" />
	<configure terrainIdx="4" pos="1131" idx="26" lv="1" islandType="6" />
	<configure terrainIdx="4" pos="1135" idx="26" lv="1" islandType="6" />
	<configure terrainIdx="4" pos="1139" idx="26" lv="1" islandType="6" />
	<configure terrainIdx="4" pos="1143" idx="26" lv="1" islandType="6" />
	<configure terrainIdx="4" pos="1147" idx="26" lv="1" islandType="6" />
	<configure terrainIdx="4" pos="1151" idx="26" lv="1" islandType="6" />
	<configure terrainIdx="4" pos="1155" idx="26" lv="1" islandType="6" />
	<configure terrainIdx="4" pos="1411" idx="26" lv="1" islandType="6" />
	<configure terrainIdx="4" pos="1415" idx="26" lv="1" islandType="6" />
	<configure terrainIdx="4" pos="1423" idx="26" lv="1" islandType="6" />
	<configure terrainIdx="4" pos="1427" idx="26" lv="1" islandType="6" />
	<configure terrainIdx="4" pos="1695" idx="26" lv="1" islandType="6" />
	<configure terrainIdx="4" pos="1699" idx="26" lv="1" islandType="6" />
	<configure terrainIdx="4" pos="1703" idx="26" lv="1" islandType="6" />
	<configure terrainIdx="4" pos="1971" idx="26" lv="1" islandType="6" />
	<configure terrainIdx="4" pos="1975" idx="26" lv="1" islandType="6" />
	<configure terrainIdx="4" pos="1979" idx="26" lv="1" islandType="6" />
	<configure terrainIdx="4" pos="2251" idx="26" lv="1" islandType="6" />
	<configure terrainIdx="4" pos="2255" idx="26" lv="1" islandType="6" />
	<configure terrainIdx="4" pos="2531" idx="26" lv="1" islandType="6" />
	<configure terrainIdx="4" pos="2535" idx="26" lv="1" islandType="6" />
	<configure terrainIdx="4" pos="2811" idx="26" lv="1" islandType="6" />
	<configure terrainIdx="4" pos="2815" idx="26" lv="1" islandType="6" />
	<configure terrainIdx="4" pos="3091" idx="26" lv="1" islandType="6" />
	<configure terrainIdx="4" pos="3371" idx="26" lv="1" islandType="6" />
	<configure terrainIdx="4" pos="3375" idx="26" lv="1" islandType="6" />
	<configure terrainIdx="4" pos="3655" idx="26" lv="1" islandType="6" />
	<configure terrainIdx="4" pos="3931" idx="26" lv="1" islandType="6" />
	<configure terrainIdx="4" pos="3935" idx="26" lv="1" islandType="6" />
	<configure terrainIdx="4" pos="4211" idx="26" lv="1" islandType="6" />
	<configure terrainIdx="4" pos="4215" idx="26" lv="1" islandType="6" />
	<configure terrainIdx="4" pos="4491" idx="26" lv="1" islandType="6" />
	<configure terrainIdx="4" pos="4495" idx="26" lv="1" islandType="6" />
	<configure terrainIdx="4" pos="4771" idx="26" lv="1" islandType="6" />
	<configure terrainIdx="4" pos="1799" idx="26" lv="1" islandType="6" />
	<configure terrainIdx="4" pos="2506" idx="26" lv="1" islandType="6" />
	<configure terrainIdx="4" pos="3733" idx="26" lv="1" islandType="6" />
	<configure terrainIdx="4" pos="2271" idx="1" lv="20" islandType="6" />
	<configure terrainIdx="4" pos="2620" idx="2" lv="20" islandType="6" />
	<configure terrainIdx="4" pos="2616" idx="2" lv="20" islandType="6" />
	<configure terrainIdx="4" pos="2896" idx="3" lv="20" islandType="6" />
	<configure terrainIdx="4" pos="2900" idx="3" lv="20" islandType="6" />
	<configure terrainIdx="4" pos="3176" idx="4" lv="20" islandType="6" />
	<configure terrainIdx="4" pos="3180" idx="4" lv="20" islandType="6" />
	<configure terrainIdx="4" pos="3456" idx="5" lv="20" islandType="6" />
	<configure terrainIdx="4" pos="3460" idx="5" lv="20" islandType="6" />
	<configure terrainIdx="4" pos="2624" idx="6" lv="20" islandType="6" />
	<configure terrainIdx="4" pos="2628" idx="6" lv="20" islandType="6" />
	<configure terrainIdx="4" pos="2632" idx="6" lv="20" islandType="6" />
	<configure terrainIdx="4" pos="2636" idx="6" lv="20" islandType="6" />
	<configure terrainIdx="4" pos="2640" idx="6" lv="20" islandType="6" />
	<configure terrainIdx="4" pos="2974" idx="7" lv="20" islandType="6" />
	<configure terrainIdx="4" pos="2979" idx="8" lv="20" islandType="6" />
	<configure terrainIdx="4" pos="3324" idx="9" lv="20" islandType="6" />
	<configure terrainIdx="4" pos="2281" idx="10" lv="20" islandType="6" />
	<configure terrainIdx="4" pos="2206" idx="11" lv="20" islandType="6" />
	<configure terrainIdx="4" pos="2276" idx="14" lv="1" islandType="6" />
	<configure terrainIdx="4" pos="2610" idx="16" lv="20" islandType="6" />
	<configure terrainIdx="4" pos="2195" idx="16" lv="20" islandType="6" />
	<configure terrainIdx="4" pos="1791" idx="16" lv="20" islandType="6" />
	<configure terrainIdx="4" pos="1788" idx="16" lv="20" islandType="6" />
	<configure terrainIdx="4" pos="3812" idx="19" lv="20" islandType="6" />
	<configure terrainIdx="4" pos="3606" idx="19" lv="20" islandType="6" />
	<configure terrainIdx="4" pos="3330" idx="19" lv="20" islandType="6" />
	<configure terrainIdx="4" pos="2988" idx="19" lv="20" islandType="6" />
	<configure terrainIdx="4" pos="4303" idx="17" lv="20" islandType="6" />
	<configure terrainIdx="4" pos="4207" idx="17" lv="20" islandType="6" />
	<configure terrainIdx="4" pos="3750" idx="17" lv="20" islandType="6" />
	<configure terrainIdx="4" pos="3544" idx="17" lv="20" islandType="6" />
	<configure terrainIdx="4" pos="4800" idx="15" lv="20" islandType="6" />
	<configure terrainIdx="4" pos="4313" idx="15" lv="20" islandType="6" />
	<configure terrainIdx="4" pos="3897" idx="15" lv="20" islandType="6" />
	<configure terrainIdx="4" pos="3622" idx="15" lv="20" islandType="6" />
	<configure terrainIdx="4" pos="3626" idx="15" lv="20" islandType="6" />
	<configure terrainIdx="4" pos="3630" idx="15" lv="20" islandType="6" />
	<configure terrainIdx="4" pos="3270" idx="18" lv="20" islandType="6" />
	<configure terrainIdx="4" pos="3275" idx="18" lv="20" islandType="6" />
	<configure terrainIdx="4" pos="3280" idx="18" lv="20" islandType="6" />
	<configure terrainIdx="4" pos="3284" idx="18" lv="20" islandType="6" />
	<configure terrainIdx="4" pos="10000" idx="13" lv="1" islandType="6" />
	<configure terrainIdx="4" pos="10001" idx="12" lv="1" islandType="6" />
	<configure terrainIdx="4" pos="10002" idx="12" lv="1" islandType="6" />
	<configure terrainIdx="4" pos="10003" idx="12" lv="1" islandType="6" />
	<configure terrainIdx="4" pos="10004" idx="12" lv="1" islandType="6" />
	<configure terrainIdx="4" pos="10005" idx="12" lv="1" islandType="6" />
	<configure terrainIdx="5" pos="142" idx="28" lv="1" islandType="6" />
	<configure terrainIdx="5" pos="147" idx="28" lv="1" islandType="6" />
	<configure terrainIdx="5" pos="152" idx="28" lv="1" islandType="6" />
	<configure terrainIdx="5" pos="157" idx="28" lv="1" islandType="6" />
	<configure terrainIdx="5" pos="162" idx="28" lv="1" islandType="6" />
	<configure terrainIdx="5" pos="167" idx="28" lv="1" islandType="6" />
	<configure terrainIdx="5" pos="177" idx="28" lv="1" islandType="6" />
	<configure terrainIdx="5" pos="182" idx="28" lv="1" islandType="6" />
	<configure terrainIdx="5" pos="187" idx="28" lv="1" islandType="6" />
	<configure terrainIdx="5" pos="192" idx="28" lv="1" islandType="6" />
	<configure terrainIdx="5" pos="197" idx="28" lv="1" islandType="6" />
	<configure terrainIdx="5" pos="202" idx="28" lv="1" islandType="6" />
	<configure terrainIdx="5" pos="207" idx="28" lv="1" islandType="6" />
	<configure terrainIdx="5" pos="492" idx="28" lv="1" islandType="6" />
	<configure terrainIdx="5" pos="497" idx="28" lv="1" islandType="6" />
	<configure terrainIdx="5" pos="502" idx="28" lv="1" islandType="6" />
	<configure terrainIdx="5" pos="507" idx="28" lv="1" islandType="6" />
	<configure terrainIdx="5" pos="517" idx="28" lv="1" islandType="6" />
	<configure terrainIdx="5" pos="522" idx="28" lv="1" islandType="6" />
	<configure terrainIdx="5" pos="527" idx="28" lv="1" islandType="6" />
	<configure terrainIdx="5" pos="537" idx="28" lv="1" islandType="6" />
	<configure terrainIdx="5" pos="542" idx="28" lv="1" islandType="6" />
	<configure terrainIdx="5" pos="547" idx="28" lv="1" islandType="6" />
	<configure terrainIdx="5" pos="552" idx="28" lv="1" islandType="6" />
	<configure terrainIdx="5" pos="557" idx="28" lv="1" islandType="6" />
	<configure terrainIdx="5" pos="842" idx="28" lv="1" islandType="6" />
	<configure terrainIdx="5" pos="847" idx="28" lv="1" islandType="6" />
	<configure terrainIdx="5" pos="1192" idx="28" lv="1" islandType="6" />
	<configure terrainIdx="5" pos="1542" idx="28" lv="1" islandType="6" />
	<configure terrainIdx="5" pos="1547" idx="28" lv="1" islandType="6" />
	<configure terrainIdx="5" pos="1892" idx="28" lv="1" islandType="6" />
	<configure terrainIdx="5" pos="1897" idx="28" lv="1" islandType="6" />
	<configure terrainIdx="5" pos="2242" idx="28" lv="1" islandType="6" />
	<configure terrainIdx="5" pos="2592" idx="28" lv="1" islandType="6" />
	<configure terrainIdx="5" pos="2597" idx="28" lv="1" islandType="6" />
	<configure terrainIdx="5" pos="2947" idx="28" lv="1" islandType="6" />
	<configure terrainIdx="5" pos="3292" idx="28" lv="1" islandType="6" />
	<configure terrainIdx="5" pos="3297" idx="28" lv="1" islandType="6" />
	<configure terrainIdx="5" pos="3647" idx="28" lv="1" islandType="6" />
	<configure terrainIdx="5" pos="3992" idx="28" lv="1" islandType="6" />
	<configure terrainIdx="5" pos="3997" idx="28" lv="1" islandType="6" />
	<configure terrainIdx="5" pos="4342" idx="28" lv="1" islandType="6" />
	<configure terrainIdx="5" pos="4692" idx="28" lv="1" islandType="6" />
	<configure terrainIdx="5" pos="4697" idx="28" lv="1" islandType="6" />
	<configure terrainIdx="5" pos="103" idx="31" lv="1" islandType="6" />
	<configure terrainIdx="5" pos="123" idx="31" lv="1" islandType="6" />
	<configure terrainIdx="5" pos="443" idx="31" lv="1" islandType="6" />
	<configure terrainIdx="5" pos="786" idx="31" lv="1" islandType="6" />
	<configure terrainIdx="5" pos="1350" idx="31" lv="1" islandType="6" />
	<configure terrainIdx="5" pos="802" idx="31" lv="1" islandType="6" />
	<configure terrainIdx="5" pos="1622" idx="31" lv="1" islandType="6" />
	<configure terrainIdx="5" pos="1128" idx="31" lv="1" islandType="6" />
	<configure terrainIdx="5" pos="2178" idx="31" lv="1" islandType="6" />
	<configure terrainIdx="5" pos="2873" idx="31" lv="1" islandType="6" />
	<configure terrainIdx="5" pos="3206" idx="31" lv="1" islandType="6" />
	<configure terrainIdx="5" pos="3573" idx="31" lv="1" islandType="6" />
	<configure terrainIdx="5" pos="3582" idx="31" lv="1" islandType="6" />
	<configure terrainIdx="5" pos="4278" idx="31" lv="1" islandType="6" />
	<configure terrainIdx="5" pos="463" idx="31" lv="1" islandType="6" />
	<configure terrainIdx="5" pos="1094" idx="31" lv="1" islandType="6" />
	<configure terrainIdx="5" pos="826" idx="31" lv="1" islandType="6" />
	<configure terrainIdx="5" pos="834" idx="31" lv="1" islandType="6" />
	<configure terrainIdx="5" pos="1781" idx="31" lv="1" islandType="6" />
	<configure terrainIdx="5" pos="851" idx="26" lv="1" islandType="6" />
	<configure terrainIdx="5" pos="859" idx="26" lv="1" islandType="6" />
	<configure terrainIdx="5" pos="863" idx="26" lv="1" islandType="6" />
	<configure terrainIdx="5" pos="867" idx="26" lv="1" islandType="6" />
	<configure terrainIdx="5" pos="875" idx="26" lv="1" islandType="6" />
	<configure terrainIdx="5" pos="1131" idx="26" lv="1" islandType="6" />
	<configure terrainIdx="5" pos="1135" idx="26" lv="1" islandType="6" />
	<configure terrainIdx="5" pos="1139" idx="26" lv="1" islandType="6" />
	<configure terrainIdx="5" pos="1143" idx="26" lv="1" islandType="6" />
	<configure terrainIdx="5" pos="1147" idx="26" lv="1" islandType="6" />
	<configure terrainIdx="5" pos="1151" idx="26" lv="1" islandType="6" />
	<configure terrainIdx="5" pos="1155" idx="26" lv="1" islandType="6" />
	<configure terrainIdx="5" pos="1411" idx="26" lv="1" islandType="6" />
	<configure terrainIdx="5" pos="1415" idx="26" lv="1" islandType="6" />
	<configure terrainIdx="5" pos="1423" idx="26" lv="1" islandType="6" />
	<configure terrainIdx="5" pos="1427" idx="26" lv="1" islandType="6" />
	<configure terrainIdx="5" pos="1695" idx="26" lv="1" islandType="6" />
	<configure terrainIdx="5" pos="1699" idx="26" lv="1" islandType="6" />
	<configure terrainIdx="5" pos="1703" idx="26" lv="1" islandType="6" />
	<configure terrainIdx="5" pos="1971" idx="26" lv="1" islandType="6" />
	<configure terrainIdx="5" pos="1975" idx="26" lv="1" islandType="6" />
	<configure terrainIdx="5" pos="1979" idx="26" lv="1" islandType="6" />
	<configure terrainIdx="5" pos="2251" idx="26" lv="1" islandType="6" />
	<configure terrainIdx="5" pos="2255" idx="26" lv="1" islandType="6" />
	<configure terrainIdx="5" pos="2531" idx="26" lv="1" islandType="6" />
	<configure terrainIdx="5" pos="2535" idx="26" lv="1" islandType="6" />
	<configure terrainIdx="5" pos="2811" idx="26" lv="1" islandType="6" />
	<configure terrainIdx="5" pos="2815" idx="26" lv="1" islandType="6" />
	<configure terrainIdx="5" pos="3091" idx="26" lv="1" islandType="6" />
	<configure terrainIdx="5" pos="3371" idx="26" lv="1" islandType="6" />
	<configure terrainIdx="5" pos="3375" idx="26" lv="1" islandType="6" />
	<configure terrainIdx="5" pos="3655" idx="26" lv="1" islandType="6" />
	<configure terrainIdx="5" pos="3931" idx="26" lv="1" islandType="6" />
	<configure terrainIdx="5" pos="3935" idx="26" lv="1" islandType="6" />
	<configure terrainIdx="5" pos="4211" idx="26" lv="1" islandType="6" />
	<configure terrainIdx="5" pos="4215" idx="26" lv="1" islandType="6" />
	<configure terrainIdx="5" pos="4491" idx="26" lv="1" islandType="6" />
	<configure terrainIdx="5" pos="4495" idx="26" lv="1" islandType="6" />
	<configure terrainIdx="5" pos="4771" idx="26" lv="1" islandType="6" />
	<configure terrainIdx="5" pos="1799" idx="26" lv="1" islandType="6" />
	<configure terrainIdx="5" pos="2506" idx="26" lv="1" islandType="6" />
	<configure terrainIdx="5" pos="3733" idx="26" lv="1" islandType="6" />
	<configure terrainIdx="5" pos="2271" idx="1" lv="12" islandType="6" />
	<configure terrainIdx="5" pos="2896" idx="3" lv="12" islandType="6" />
	<configure terrainIdx="5" pos="2610" idx="16" lv="12" islandType="6" />
	<configure terrainIdx="5" pos="4303" idx="17" lv="12" islandType="6" />
	<configure terrainIdx="5" pos="4207" idx="17" lv="12" islandType="6" />
	<configure terrainIdx="5" pos="3750" idx="17" lv="12" islandType="6" />
	<configure terrainIdx="5" pos="3544" idx="17" lv="12" islandType="6" />
	<configure terrainIdx="5" pos="4800" idx="17" lv="12" islandType="6" />
	<configure terrainIdx="5" pos="4313" idx="17" lv="12" islandType="6" />
	<configure terrainIdx="6" pos="142" idx="28" lv="1" islandType="6" />
	<configure terrainIdx="6" pos="147" idx="28" lv="1" islandType="6" />
	<configure terrainIdx="6" pos="152" idx="28" lv="1" islandType="6" />
	<configure terrainIdx="6" pos="157" idx="28" lv="1" islandType="6" />
	<configure terrainIdx="6" pos="162" idx="28" lv="1" islandType="6" />
	<configure terrainIdx="6" pos="167" idx="28" lv="1" islandType="6" />
	<configure terrainIdx="6" pos="177" idx="28" lv="1" islandType="6" />
	<configure terrainIdx="6" pos="182" idx="28" lv="1" islandType="6" />
	<configure terrainIdx="6" pos="187" idx="28" lv="1" islandType="6" />
	<configure terrainIdx="6" pos="192" idx="28" lv="1" islandType="6" />
	<configure terrainIdx="6" pos="197" idx="28" lv="1" islandType="6" />
	<configure terrainIdx="6" pos="202" idx="28" lv="1" islandType="6" />
	<configure terrainIdx="6" pos="207" idx="28" lv="1" islandType="6" />
	<configure terrainIdx="6" pos="492" idx="28" lv="1" islandType="6" />
	<configure terrainIdx="6" pos="497" idx="28" lv="1" islandType="6" />
	<configure terrainIdx="6" pos="502" idx="28" lv="1" islandType="6" />
	<configure terrainIdx="6" pos="507" idx="28" lv="1" islandType="6" />
	<configure terrainIdx="6" pos="517" idx="28" lv="1" islandType="6" />
	<configure terrainIdx="6" pos="522" idx="28" lv="1" islandType="6" />
	<configure terrainIdx="6" pos="527" idx="28" lv="1" islandType="6" />
	<configure terrainIdx="6" pos="537" idx="28" lv="1" islandType="6" />
	<configure terrainIdx="6" pos="542" idx="28" lv="1" islandType="6" />
	<configure terrainIdx="6" pos="547" idx="28" lv="1" islandType="6" />
	<configure terrainIdx="6" pos="552" idx="28" lv="1" islandType="6" />
	<configure terrainIdx="6" pos="557" idx="28" lv="1" islandType="6" />
	<configure terrainIdx="6" pos="842" idx="28" lv="1" islandType="6" />
	<configure terrainIdx="6" pos="847" idx="28" lv="1" islandType="6" />
	<configure terrainIdx="6" pos="1192" idx="28" lv="1" islandType="6" />
	<configure terrainIdx="6" pos="1542" idx="28" lv="1" islandType="6" />
	<configure terrainIdx="6" pos="1547" idx="28" lv="1" islandType="6" />
	<configure terrainIdx="6" pos="1892" idx="28" lv="1" islandType="6" />
	<configure terrainIdx="6" pos="1897" idx="28" lv="1" islandType="6" />
	<configure terrainIdx="6" pos="2242" idx="28" lv="1" islandType="6" />
	<configure terrainIdx="6" pos="2592" idx="28" lv="1" islandType="6" />
	<configure terrainIdx="6" pos="2597" idx="28" lv="1" islandType="6" />
	<configure terrainIdx="6" pos="2947" idx="28" lv="1" islandType="6" />
	<configure terrainIdx="6" pos="3292" idx="28" lv="1" islandType="6" />
	<configure terrainIdx="6" pos="3297" idx="28" lv="1" islandType="6" />
	<configure terrainIdx="6" pos="3647" idx="28" lv="1" islandType="6" />
	<configure terrainIdx="6" pos="3992" idx="28" lv="1" islandType="6" />
	<configure terrainIdx="6" pos="3997" idx="28" lv="1" islandType="6" />
	<configure terrainIdx="6" pos="4342" idx="28" lv="1" islandType="6" />
	<configure terrainIdx="6" pos="4692" idx="28" lv="1" islandType="6" />
	<configure terrainIdx="6" pos="4697" idx="28" lv="1" islandType="6" />
	<configure terrainIdx="6" pos="103" idx="31" lv="1" islandType="6" />
	<configure terrainIdx="6" pos="123" idx="31" lv="1" islandType="6" />
	<configure terrainIdx="6" pos="443" idx="31" lv="1" islandType="6" />
	<configure terrainIdx="6" pos="786" idx="31" lv="1" islandType="6" />
	<configure terrainIdx="6" pos="1350" idx="31" lv="1" islandType="6" />
	<configure terrainIdx="6" pos="802" idx="31" lv="1" islandType="6" />
	<configure terrainIdx="6" pos="1622" idx="31" lv="1" islandType="6" />
	<configure terrainIdx="6" pos="1128" idx="31" lv="1" islandType="6" />
	<configure terrainIdx="6" pos="2178" idx="31" lv="1" islandType="6" />
	<configure terrainIdx="6" pos="2873" idx="31" lv="1" islandType="6" />
	<configure terrainIdx="6" pos="3206" idx="31" lv="1" islandType="6" />
	<configure terrainIdx="6" pos="3573" idx="31" lv="1" islandType="6" />
	<configure terrainIdx="6" pos="3582" idx="31" lv="1" islandType="6" />
	<configure terrainIdx="6" pos="4278" idx="31" lv="1" islandType="6" />
	<configure terrainIdx="6" pos="463" idx="31" lv="1" islandType="6" />
	<configure terrainIdx="6" pos="1094" idx="31" lv="1" islandType="6" />
	<configure terrainIdx="6" pos="826" idx="31" lv="1" islandType="6" />
	<configure terrainIdx="6" pos="834" idx="31" lv="1" islandType="6" />
	<configure terrainIdx="6" pos="1781" idx="31" lv="1" islandType="6" />
	<configure terrainIdx="6" pos="851" idx="26" lv="1" islandType="6" />
	<configure terrainIdx="6" pos="859" idx="26" lv="1" islandType="6" />
	<configure terrainIdx="6" pos="863" idx="26" lv="1" islandType="6" />
	<configure terrainIdx="6" pos="867" idx="26" lv="1" islandType="6" />
	<configure terrainIdx="6" pos="875" idx="26" lv="1" islandType="6" />
	<configure terrainIdx="6" pos="1131" idx="26" lv="1" islandType="6" />
	<configure terrainIdx="6" pos="1135" idx="26" lv="1" islandType="6" />
	<configure terrainIdx="6" pos="1139" idx="26" lv="1" islandType="6" />
	<configure terrainIdx="6" pos="1143" idx="26" lv="1" islandType="6" />
	<configure terrainIdx="6" pos="1147" idx="26" lv="1" islandType="6" />
	<configure terrainIdx="6" pos="1151" idx="26" lv="1" islandType="6" />
	<configure terrainIdx="6" pos="1155" idx="26" lv="1" islandType="6" />
	<configure terrainIdx="6" pos="1411" idx="26" lv="1" islandType="6" />
	<configure terrainIdx="6" pos="1415" idx="26" lv="1" islandType="6" />
	<configure terrainIdx="6" pos="1423" idx="26" lv="1" islandType="6" />
	<configure terrainIdx="6" pos="1427" idx="26" lv="1" islandType="6" />
	<configure terrainIdx="6" pos="1695" idx="26" lv="1" islandType="6" />
	<configure terrainIdx="6" pos="1699" idx="26" lv="1" islandType="6" />
	<configure terrainIdx="6" pos="1703" idx="26" lv="1" islandType="6" />
	<configure terrainIdx="6" pos="1971" idx="26" lv="1" islandType="6" />
	<configure terrainIdx="6" pos="1975" idx="26" lv="1" islandType="6" />
	<configure terrainIdx="6" pos="1979" idx="26" lv="1" islandType="6" />
	<configure terrainIdx="6" pos="2251" idx="26" lv="1" islandType="6" />
	<configure terrainIdx="6" pos="2255" idx="26" lv="1" islandType="6" />
	<configure terrainIdx="6" pos="2531" idx="26" lv="1" islandType="6" />
	<configure terrainIdx="6" pos="2535" idx="26" lv="1" islandType="6" />
	<configure terrainIdx="6" pos="2811" idx="26" lv="1" islandType="6" />
	<configure terrainIdx="6" pos="2815" idx="26" lv="1" islandType="6" />
	<configure terrainIdx="6" pos="3091" idx="26" lv="1" islandType="6" />
	<configure terrainIdx="6" pos="3371" idx="26" lv="1" islandType="6" />
	<configure terrainIdx="6" pos="3375" idx="26" lv="1" islandType="6" />
	<configure terrainIdx="6" pos="3655" idx="26" lv="1" islandType="6" />
	<configure terrainIdx="6" pos="3931" idx="26" lv="1" islandType="6" />
	<configure terrainIdx="6" pos="3935" idx="26" lv="1" islandType="6" />
	<configure terrainIdx="6" pos="4211" idx="26" lv="1" islandType="6" />
	<configure terrainIdx="6" pos="4215" idx="26" lv="1" islandType="6" />
	<configure terrainIdx="6" pos="4491" idx="26" lv="1" islandType="6" />
	<configure terrainIdx="6" pos="4495" idx="26" lv="1" islandType="6" />
	<configure terrainIdx="6" pos="4771" idx="26" lv="1" islandType="6" />
	<configure terrainIdx="6" pos="1799" idx="26" lv="1" islandType="6" />
	<configure terrainIdx="6" pos="2506" idx="26" lv="1" islandType="6" />
	<configure terrainIdx="6" pos="3733" idx="26" lv="1" islandType="6" />
	<configure terrainIdx="6" pos="2271" idx="1" lv="16" islandType="6" />
	<configure terrainIdx="6" pos="2979" idx="8" lv="16" islandType="6" />
	<configure terrainIdx="6" pos="2610" idx="16" lv="16" islandType="6" />
	<configure terrainIdx="6" pos="2195" idx="16" lv="16" islandType="6" />
	<configure terrainIdx="6" pos="3626" idx="18" lv="16" islandType="6" />
	<configure terrainIdx="6" pos="3630" idx="18" lv="16" islandType="6" />
	<configure terrainIdx="6" pos="3270" idx="18" lv="16" islandType="6" />
	<configure terrainIdx="6" pos="3275" idx="18" lv="16" islandType="6" />
	<configure terrainIdx="6" pos="3280" idx="18" lv="16" islandType="6" />
	<configure terrainIdx="6" pos="3284" idx="18" lv="16" islandType="6" />
	<configure terrainIdx="7" pos="142" idx="28" lv="1" islandType="6" />
	<configure terrainIdx="7" pos="147" idx="28" lv="1" islandType="6" />
	<configure terrainIdx="7" pos="152" idx="28" lv="1" islandType="6" />
	<configure terrainIdx="7" pos="157" idx="28" lv="1" islandType="6" />
	<configure terrainIdx="7" pos="162" idx="28" lv="1" islandType="6" />
	<configure terrainIdx="7" pos="167" idx="28" lv="1" islandType="6" />
	<configure terrainIdx="7" pos="177" idx="28" lv="1" islandType="6" />
	<configure terrainIdx="7" pos="182" idx="28" lv="1" islandType="6" />
	<configure terrainIdx="7" pos="187" idx="28" lv="1" islandType="6" />
	<configure terrainIdx="7" pos="192" idx="28" lv="1" islandType="6" />
	<configure terrainIdx="7" pos="197" idx="28" lv="1" islandType="6" />
	<configure terrainIdx="7" pos="202" idx="28" lv="1" islandType="6" />
	<configure terrainIdx="7" pos="207" idx="28" lv="1" islandType="6" />
	<configure terrainIdx="7" pos="492" idx="28" lv="1" islandType="6" />
	<configure terrainIdx="7" pos="497" idx="28" lv="1" islandType="6" />
	<configure terrainIdx="7" pos="502" idx="28" lv="1" islandType="6" />
	<configure terrainIdx="7" pos="507" idx="28" lv="1" islandType="6" />
	<configure terrainIdx="7" pos="517" idx="28" lv="1" islandType="6" />
	<configure terrainIdx="7" pos="522" idx="28" lv="1" islandType="6" />
	<configure terrainIdx="7" pos="527" idx="28" lv="1" islandType="6" />
	<configure terrainIdx="7" pos="537" idx="28" lv="1" islandType="6" />
	<configure terrainIdx="7" pos="542" idx="28" lv="1" islandType="6" />
	<configure terrainIdx="7" pos="547" idx="28" lv="1" islandType="6" />
	<configure terrainIdx="7" pos="552" idx="28" lv="1" islandType="6" />
	<configure terrainIdx="7" pos="557" idx="28" lv="1" islandType="6" />
	<configure terrainIdx="7" pos="842" idx="28" lv="1" islandType="6" />
	<configure terrainIdx="7" pos="847" idx="28" lv="1" islandType="6" />
	<configure terrainIdx="7" pos="1192" idx="28" lv="1" islandType="6" />
	<configure terrainIdx="7" pos="1542" idx="28" lv="1" islandType="6" />
	<configure terrainIdx="7" pos="1547" idx="28" lv="1" islandType="6" />
	<configure terrainIdx="7" pos="1892" idx="28" lv="1" islandType="6" />
	<configure terrainIdx="7" pos="1897" idx="28" lv="1" islandType="6" />
	<configure terrainIdx="7" pos="2242" idx="28" lv="1" islandType="6" />
	<configure terrainIdx="7" pos="2592" idx="28" lv="1" islandType="6" />
	<configure terrainIdx="7" pos="2597" idx="28" lv="1" islandType="6" />
	<configure terrainIdx="7" pos="2947" idx="28" lv="1" islandType="6" />
	<configure terrainIdx="7" pos="3292" idx="28" lv="1" islandType="6" />
	<configure terrainIdx="7" pos="3297" idx="28" lv="1" islandType="6" />
	<configure terrainIdx="7" pos="3647" idx="28" lv="1" islandType="6" />
	<configure terrainIdx="7" pos="3992" idx="28" lv="1" islandType="6" />
	<configure terrainIdx="7" pos="3997" idx="28" lv="1" islandType="6" />
	<configure terrainIdx="7" pos="4342" idx="28" lv="1" islandType="6" />
	<configure terrainIdx="7" pos="4692" idx="28" lv="1" islandType="6" />
	<configure terrainIdx="7" pos="4697" idx="28" lv="1" islandType="6" />
	<configure terrainIdx="7" pos="103" idx="31" lv="1" islandType="6" />
	<configure terrainIdx="7" pos="123" idx="31" lv="1" islandType="6" />
	<configure terrainIdx="7" pos="443" idx="31" lv="1" islandType="6" />
	<configure terrainIdx="7" pos="786" idx="31" lv="1" islandType="6" />
	<configure terrainIdx="7" pos="1350" idx="31" lv="1" islandType="6" />
	<configure terrainIdx="7" pos="802" idx="31" lv="1" islandType="6" />
	<configure terrainIdx="7" pos="1622" idx="31" lv="1" islandType="6" />
	<configure terrainIdx="7" pos="1128" idx="31" lv="1" islandType="6" />
	<configure terrainIdx="7" pos="2178" idx="31" lv="1" islandType="6" />
	<configure terrainIdx="7" pos="2873" idx="31" lv="1" islandType="6" />
	<configure terrainIdx="7" pos="3206" idx="31" lv="1" islandType="6" />
	<configure terrainIdx="7" pos="3573" idx="31" lv="1" islandType="6" />
	<configure terrainIdx="7" pos="3582" idx="31" lv="1" islandType="6" />
	<configure terrainIdx="7" pos="4278" idx="31" lv="1" islandType="6" />
	<configure terrainIdx="7" pos="463" idx="31" lv="1" islandType="6" />
	<configure terrainIdx="7" pos="1094" idx="31" lv="1" islandType="6" />
	<configure terrainIdx="7" pos="826" idx="31" lv="1" islandType="6" />
	<configure terrainIdx="7" pos="834" idx="31" lv="1" islandType="6" />
	<configure terrainIdx="7" pos="1781" idx="31" lv="1" islandType="6" />
	<configure terrainIdx="7" pos="851" idx="26" lv="1" islandType="6" />
	<configure terrainIdx="7" pos="859" idx="26" lv="1" islandType="6" />
	<configure terrainIdx="7" pos="863" idx="26" lv="1" islandType="6" />
	<configure terrainIdx="7" pos="867" idx="26" lv="1" islandType="6" />
	<configure terrainIdx="7" pos="875" idx="26" lv="1" islandType="6" />
	<configure terrainIdx="7" pos="1131" idx="26" lv="1" islandType="6" />
	<configure terrainIdx="7" pos="1135" idx="26" lv="1" islandType="6" />
	<configure terrainIdx="7" pos="1139" idx="26" lv="1" islandType="6" />
	<configure terrainIdx="7" pos="1143" idx="26" lv="1" islandType="6" />
	<configure terrainIdx="7" pos="1147" idx="26" lv="1" islandType="6" />
	<configure terrainIdx="7" pos="1151" idx="26" lv="1" islandType="6" />
	<configure terrainIdx="7" pos="1155" idx="26" lv="1" islandType="6" />
	<configure terrainIdx="7" pos="1411" idx="26" lv="1" islandType="6" />
	<configure terrainIdx="7" pos="1415" idx="26" lv="1" islandType="6" />
	<configure terrainIdx="7" pos="1423" idx="26" lv="1" islandType="6" />
	<configure terrainIdx="7" pos="1427" idx="26" lv="1" islandType="6" />
	<configure terrainIdx="7" pos="1695" idx="26" lv="1" islandType="6" />
	<configure terrainIdx="7" pos="1699" idx="26" lv="1" islandType="6" />
	<configure terrainIdx="7" pos="1703" idx="26" lv="1" islandType="6" />
	<configure terrainIdx="7" pos="1971" idx="26" lv="1" islandType="6" />
	<configure terrainIdx="7" pos="1975" idx="26" lv="1" islandType="6" />
	<configure terrainIdx="7" pos="1979" idx="26" lv="1" islandType="6" />
	<configure terrainIdx="7" pos="2251" idx="26" lv="1" islandType="6" />
	<configure terrainIdx="7" pos="2255" idx="26" lv="1" islandType="6" />
	<configure terrainIdx="7" pos="2531" idx="26" lv="1" islandType="6" />
	<configure terrainIdx="7" pos="2535" idx="26" lv="1" islandType="6" />
	<configure terrainIdx="7" pos="2811" idx="26" lv="1" islandType="6" />
	<configure terrainIdx="7" pos="2815" idx="26" lv="1" islandType="6" />
	<configure terrainIdx="7" pos="3091" idx="26" lv="1" islandType="6" />
	<configure terrainIdx="7" pos="3371" idx="26" lv="1" islandType="6" />
	<configure terrainIdx="7" pos="3375" idx="26" lv="1" islandType="6" />
	<configure terrainIdx="7" pos="3655" idx="26" lv="1" islandType="6" />
	<configure terrainIdx="7" pos="3931" idx="26" lv="1" islandType="6" />
	<configure terrainIdx="7" pos="3935" idx="26" lv="1" islandType="6" />
	<configure terrainIdx="7" pos="4211" idx="26" lv="1" islandType="6" />
	<configure terrainIdx="7" pos="4215" idx="26" lv="1" islandType="6" />
	<configure terrainIdx="7" pos="4491" idx="26" lv="1" islandType="6" />
	<configure terrainIdx="7" pos="4495" idx="26" lv="1" islandType="6" />
	<configure terrainIdx="7" pos="4771" idx="26" lv="1" islandType="6" />
	<configure terrainIdx="7" pos="1799" idx="26" lv="1" islandType="6" />
	<configure terrainIdx="7" pos="2506" idx="26" lv="1" islandType="6" />
	<configure terrainIdx="7" pos="3733" idx="26" lv="1" islandType="6" />
	<configure terrainIdx="7" pos="2271" idx="1" lv="5" islandType="6" />
	<configure terrainIdx="7" pos="3324" idx="9" lv="5" islandType="6" />
	<configure terrainIdx="7" pos="4800" idx="15" lv="5" islandType="6" />
	<configure terrainIdx="7" pos="4313" idx="15" lv="5" islandType="6" />
	<configure terrainIdx="7" pos="3897" idx="15" lv="5" islandType="6" />
</configures>