<?xml version="1.0" encoding="UTF-8" standalone="yes"?>
<configures>
	<configure id="七天登陆" value="七日登錄" />
	<configure id="在线奖励" value="線上獎勵" />
	<configure id="每日任务" value="每日任務" />
	<configure id="等级冲刺" value="等級衝刺" />
	<configure id="基地礼包" value="基地禮包" />
	<configure id="关卡奖励" value="關卡獎勵" />
	<configure id="排行榜" value="排行榜" />
	<configure id="勇者无敌" value="勇者無敵榜" />
	<configure id="冲级领钻石" value="沖級領鑽石" />
	<configure id="今日首充" value="今日首充" />
	<configure id="充值大礼" value="儲值大禮" />
	<configure id="单笔充值" value="單筆儲值" />
	<configure id="充值排行" value="儲值排行" />
	<configure id="特惠礼包" value="特惠禮包" />
	<configure id="累计消费" value="累計消費" />
	<configure id="消费排行" value="消費排行" />
	<configure id="角色达到LV.5" value="角色達到LV.5" />
	<configure id="角色达到LV.10" value="角色達到LV.10" />
	<configure id="角色达到LV.20" value="角色達到LV.20" />
	<configure id="角色达到LV.30" value="角色達到LV.30" />
	<configure id="角色达到LV.40" value="角色達到LV.40" />
	<configure id="角色达到LV.50" value="角色達到LV.50" />
	<configure id="角色达到LV.60" value="角色達到LV.60" />
	<configure id="主基地达到LV.3" value="主基地達到LV.3" />
	<configure id="主基地达到LV.5" value="主基地達到LV.5" />
	<configure id="主基地达到LV.8" value="主基地達到LV.8" />
	<configure id="主基地达到LV.10" value="主基地達到LV.10" />
	<configure id="主基地达到LV.15" value="主基地達到LV.15" />
	<configure id="主基地达到LV.20" value="主基地達到LV.20" />
	<configure id="通过副本布拉德利要塞" value="通過副本布拉德利要塞" />
	<configure id="通过副本乌拉尔山" value="通過副本烏拉爾山" />
	<configure id="通过副本黑森林" value="通過副本黑森林" />
	<configure id="通过副本光棱科技站" value="通過副本光棱科技站" />
	<configure id="通过副本电磁科技站" value="通過副本電磁科技站" />
	<configure id="通关副本消灭尤里" value="通關副本消滅尤裏" />
	<configure id="通关副本寸土必争" value="通關副本寸土必爭" />
	<configure id="通关副本琉球群岛" value="通關副本琉球群島" />
	<configure id="通关副本浮岛堡垒" value="通關副本浮島堡壘" />
	<configure id="通关副本昨日重现" value="通關副本昨日重現" />
	<configure id="通关副本富士山之战" value="通關副本富士山之戰" />
	<configure id="通关副本光阴似箭" value="通關副本光陰似箭" />
	<configure id="通关副本梦一场" value="通關副本夢一場" />
	<configure id="通关副本集中攻击" value="通關副本集中攻擊" />
	<configure id="通关副本洗脑" value="通關副本洗腦" />
	<configure id="通关副本沙漠奇袭" value="通關副本沙漠奇襲" />
	<configure id="通关副本复制中心" value="通關副本複製中心" />
	<configure id="通关副本秘密基地" value="通關副本秘密基地" />
	<configure id="通关副本极地之战" value="通關副本極地之戰" />
	<configure id="通关副本尤里的堡垒" value="通關副本尤裏的堡壘" />
	<configure id="进入排行榜100名以内" value="進入排行榜100名以內" />
	<configure id="进入排行榜50名以内" value="進入排行榜50名以內" />
	<configure id="进入排行榜30名以内" value="進入排行榜30名以內" />
	<configure id="进入排行榜20名以内" value="進入排行榜20名以內" />
	<configure id="进入排行榜10名以内" value="進入排行榜10名以內" />
	<configure id="成为排行榜冠军" value="成為排行榜冠軍" />
	<configure id="冲榜排行第6名" value="沖榜排行第6名" />
	<configure id="冲榜排行第5名" value="沖榜排行第5名" />
	<configure id="冲榜排行第4名" value="沖榜排行第4名" />
	<configure id="冲榜排行第3名" value="沖榜排行第3名" />
	<configure id="冲榜排行第2名" value="沖榜排行第2名" />
	<configure id="冲榜排行第1名" value="沖榜排行第1名" />
	<configure id="累积在线5分钟" value="累積線上5分鐘" />
	<configure id="累积在线10分钟" value="累積線上10分鐘" />
	<configure id="累积在线30分钟" value="累積線上30分鐘" />
	<configure id="累积在线1小时" value="累積線上1小時" />
	<configure id="累积在线2小时" value="累積線上2小時" />
	<configure id="前20位角色等级达到LV.30的玩家可以领取" value="前20位角色等級達到LV.30的玩家可以領取" />
	<configure id="前20位角色等级达到LV.45的玩家可以领取" value="前20位角色等級達到LV.45的玩家可以領取" />
	<configure id="前20位角色等级达到LV.60的玩家可以领取" value="前20位角色等級達到LV.60的玩家可以領取" />
	<configure id="当日充值60钻石" value="當日儲值60鑽石" />
	<configure id="首次充值购买任意钻石，" value="首次儲值購買任意鑽石，" />
	<configure id="单笔充值300钻石，" value="單筆儲值300鑽石，" />
	<configure id="单笔充值680钻石，" value="單筆儲值680鑽石，" />
	<configure id="单笔充值1280钻石，" value="單筆儲值1280鑽石，" />
	<configure id="单笔充值3280钻石，" value="單筆儲值3280鑽石，" />
	<configure id="单笔充值6480钻石，" value="單筆儲值6480鑽石，" />
	<configure id="充值第一" value="儲值第一" />
	<configure id="充值第二" value="儲值第二" />
	<configure id="充值第三" value="儲值第三" />
	<configure id="花费999钻石，即可获得价值1999钻石的特惠大礼包" value="花費999鑽石，即可獲得價值1999鑽石的特惠大禮包" />
	<configure id="花费1999钻石，即可获得价值3999钻石的特惠大礼包" value="花費1999鑽石，即可獲得價值3999鑽石的特惠大禮包" />
	<configure id="花费3999钻石，即可获得价值5999钻石的特惠大礼包" value="花費3999鑽石，即可獲得價值5999鑽石的特惠大禮包" />
	<configure id="活动期间内累计消费999钻" value="活動期間內消費999鑽" />
	<configure id="消费第一" value="消費第一" />
	<configure id="消费第二" value="消費第二" />
	<configure id="消费第三" value="消費第三" />
	<configure id="活动" value="活動" />
	<configure id="活动时间：" value="活動時間：" />
	<configure id="奖励数量：" value="獎勵數量：" />
	<configure id="有限" value="有限" />
	<configure id="无限" value="無限" />
	<configure id="领取" value="領取" />
	<configure id="查看已领玩家" value="查看已領玩家" />
	<configure id="未达成" value="未達成" />
	<configure id="永久" value="永久" />
	<configure id="不限量" value="不限量" />
	<configure id="在线时间" value="線上時間" />
	<configure id="奖励已领完" value="獎勵已領完" />
	<configure id="充值" value="儲值" />
	<configure id="活动时间" value="活動時間" />
	<configure id="购买" value="購買" />
	<configure id="领取奖励" value="領取獎勵" />
	<configure id="领取次数" value="領取次數" />
	<configure id="跳转" value="跳转" />
	<configure id="可获得:" value="可獲得:" />
	<configure id="充值就送大礼！" value="充值就送大禮！" />
	<configure id="首次充值购买" value="首次充值購買" />
	<configure id="钻石，" value="鑽石，" />
	<configure id="可获得：" value="可獲得：" />
	<configure id="活动期间累计消费" value="活動期間累計消費" />
	<configure id="钻" value="鑽" />
	<configure id="任意 " value="任意" />
	<configure id="已领取" value="已領取" />
	<configure id="可领取" value="可領取" />
</configures>